tui/__init__.py
tui/chat_styles.tcss
tui/chat_tui.py
tui/pomni_tui_ss.jpeg
pomni-0.1.7.dist-info/WHEEL
pomni-0.1.7.dist-info/entry_points.txt
pomni-0.1.7.dist-info/METADATA
pomni-0.1.7.dist-info/RECORD
